superphot/__init__.py
superphot/_version.py
superphot/classify.py
superphot/extract.py
superphot/fit.py
superphot/optimize.py
superphot/util.py
superphot-1.2.0.dist-info/AUTHORS.rst
superphot-1.2.0.dist-info/LICENSE
superphot-1.2.0.dist-info/METADATA
superphot-1.2.0.dist-info/WHEEL
superphot-1.2.0.dist-info/entry_points.txt
superphot-1.2.0.dist-info/top_level.txt
superphot-1.2.0.dist-info/RECORD
