Metadata-Version: 2.1
Name: superphot
Version: 1.2.0
Summary: Photometric classification of supernovae
Home-page: https://griffin-h.github.io/superphot
Author: Griffin Hosseinzadeh & Frederick Dauphin
Author-email: griffin0@arizona.edu
License: GNU General Public License v2 (GPLv2)
Platform: UNKNOWN
Classifier: Programming Language :: Python :: 3
Classifier: Development Status :: 5 - Production/Stable
Classifier: Natural Language :: English
Requires-Python: >=3.6
Requires-Dist: astropy
Requires-Dist: matplotlib
Requires-Dist: numpy
Requires-Dist: scipy
Requires-Dist: theano
Requires-Dist: pymc3
Requires-Dist: scikit-learn
Requires-Dist: imbalanced-learn
Requires-Dist: arviz
Requires-Dist: tqdm
